playbaghchal/PlayGame.py
playbaghchal/__init__.py
playbaghchal/button.py
playbaghchal/assets/Goat_win.png
playbaghchal/assets/HumanvsAI.png
playbaghchal/assets/HumanvsHuman.png
playbaghchal/assets/Play_Again.png
playbaghchal/assets/Quit.png
playbaghchal/assets/Start.png
playbaghchal/assets/Tiger_win.png
playbaghchal/assets/advance.png
playbaghchal/assets/asGoat.png
playbaghchal/assets/asTiger.png
playbaghchal/assets/easy.png
playbaghchal/assets/forest.png
playbaghchal/assets/goat.png
playbaghchal/assets/medium.png
playbaghchal/assets/tiger.png
playbaghchal/assets/wood.png
playbaghchal-3.0.0.dist-info/licenses/LICENSE
playbaghchal-3.0.0.dist-info/File Structure.txt
playbaghchal-3.0.0.dist-info/METADATA
playbaghchal-3.0.0.dist-info/WHEEL
playbaghchal-3.0.0.dist-info/entry_points.txt
playbaghchal-3.0.0.dist-info/top_level.txt
playbaghchal-3.0.0.dist-info/RECORD
