Metadata-Version: 2.4
Name: PlayBaghChal
Version: 3.0.0
Summary: A Pygame implementation of the Bagh-Chal (Tiger and Goat) board game.
Home-page: https://github.com/bhishanP/PlayBaghChal
Author: Bhishan Pangeni
Author-email: bhishanpangeni2003@gmail.com
Keywords: pygame baghchal tiger goat board game
Classifier: Programming Language :: Python :: 3
Classifier: License :: OSI Approved :: MIT License
Classifier: Operating System :: OS Independent
Requires-Python: >=3.6
License-File: LICENSE
Requires-Dist: pygame
Dynamic: author
Dynamic: author-email
Dynamic: classifier
Dynamic: description
Dynamic: description-content-type
Dynamic: home-page
Dynamic: keywords
Dynamic: license-file
Dynamic: requires-dist
Dynamic: requires-python
Dynamic: summary
